[
  {
    "_id": "627ac5fb936c0a8e40d726e5"
  },
  {
    "_id": "627ac5fb29d748624c56056c"
  },
  {
    "_id": "627ac5fbb69586fddc2da699"
  },
  {
    "_id": "627ac5fb916c7946d4a6ebc8"
  },
  {
    "_id": "627ac5fb2faa4f2b5f8dc5af"
  },
  {
    "_id": "627ac5fb88bd6a62b55e1ba5"
  },
  {
    "_id": "627ac5fbf1cd2cd003797707"
  },
  {
    "_id": "627ac5fb5e242a594b0657fc"
  },
  {
    "_id": "627ac5fb8cc5240ac31489e6"
  },
  {
    "_id": "627ac5fbfab159ae8ea52fb0"
  },
  {
    "_id": "627ac5fb3dd0493181301317"
  },
  {
    "_id": "627ac5fb723fc217eaf5a6b4"
  },
  {
    "_id": "627ac5fb5b1b4823f2476871"
  },
  {
    "_id": "627ac5fba82aea61b91dd1d7"
  },
  {
    "_id": "627ac5fb00aa47e2faa64cd7"
  },
  {
    "_id": "627ac5fb7a4f625b79355b34"
  },
  {
    "_id": "627ac5fb7e2fd8a79c2e5aea"
  },
  {
    "_id": "627ac5fbffb4f61b985c2a98"
  },
  {
    "_id": "627ac5fbe4dbda0918866216"
  },
  {
    "_id": "627ac5fb738f27e6e7391c62"
  },
  {
    "_id": "627ac5fb186f71ad51fec34f"
  },
  {
    "_id": "627ac5fb04602aa09fa785ed"
  },
  {
    "_id": "627ac5fb579704324498cba7"
  },
  {
    "_id": "627ac5fb66428e02814a305e"
  },
  {
    "_id": "627ac5fb66de676a1c9e29e8"
  },
  {
    "_id": "627ac5fb094044392e3d11c1"
  },
  {
    "_id": "627ac5fb25afe40089a2e3c5"
  },
  {
    "_id": "627ac5fbd958b151545ba2e3"
  },
  {
    "_id": "627ac5fbb41347429ed3e381"
  },
  {
    "_id": "627ac5fb390b7890abe78532"
  },
  {
    "_id": "627ac5fb4cf1cdc5a4c35597"
  },
  {
    "_id": "627ac5fbfdf79288cbf56d65"
  },
  {
    "_id": "627ac5fb9e5f9d692abd66c8"
  },
  {
    "_id": "627ac5fb6e4cdf17ffaa36fd"
  },
  {
    "_id": "627ac5fb3bcfe80dd1539df4"
  },
  {
    "_id": "627ac5fb9b98001302bc672f"
  },
  {
    "_id": "627ac5fb1533bfe74f14220f"
  }
]
